[
  {
    "id": 1,
    "category": ["Chill", "Dance"],
    "title": "Dancing with a stranger",
    "artist": "Sam Smith",
    "src": "https://musicfeed.ir/files/2019/07/Sam-Smith-Normani-Dancing-With-A-Stranger-128.mp3",
    "cover": "assets/covers/dancing-with-a-stranger.png"
  },
  {
    "id": 2,
    "category": ["Acoustic", "Chill"],
    "title": "Call out my name",
    "artist": "The Weeknd",
    "src": "https://musicfeed.ir/files/2020/06/Call-Out-My-Name-THE-WEEKND.mp3",
    "cover": "assets/covers/call-out-my-name.jpg"
  },
  {
    "id": 3,
    "category": ["Acoustic", "Slow"],
    "title": "Blue jeans",
    "artist": "Lana Del Rey",
    "src": "https://musicfeed.ir/files/2019/07/Lana-Del-Rey-Blue-Jeans-128.mp3",
    "cover": "assets/covers/blue-jeans.jpg"
  },
  {
    "id": 4,
    "category": ["Workout", "Dance"],
    "title": "Blinding lights",
    "artist": "The Weeknd",
    "src": "https://musicfeed.ir/files/dir/2020/12/The%20Weeknd%20%20%20ROSALIA%20Blinding%20Lights%20(Remix).mp3",
    "cover": "assets/covers/blinding-lights.jpg"
  },
  {
    "id": 5,
    "category": ["Rap"],
    "title": "I'm not afraid",
    "artist": "Eminem",
    "src": "https://musicfeed.ir/files/2020/03/Eminem-Not-Afraid.mp3",
    "cover": "assets/covers/not-afraid.jpg"
  },
  {
    "id": 6,
    "category": ["Rap", "Chill"],
    "title": "Space bound",
    "artist": "Eminem",
    "src": "https://musicfeed.ir/files/2020/02/Eminem-Space-Bound-musicfeed.ir_.mp3",
    "cover": "assets/covers/space-bound.jpg"
  },
  {
    "id": 7,
    "category": ["Rap", "Dance", "Workout"],
    "title": "Dark horse",
    "artist": "Katy Perry",
    "src": "https://musicfeed.ir/files/2020/03/Katy-Perry-Dark-Horse-musicfeed.ir_.mp3",
    "cover": "assets/covers/dark-horse.png"
  },
  {
    "id": 8,
    "category": ["Dance"],
    "title": "Roar",
    "artist": "Katy Perry",
    "src": "https://musicfeed.ir/files/dir/2020/10/Katy%20Perry%20Roar.mp3",
    "cover": "assets/covers/roar.png"
  },
  {
    "id": 9,
    "category": ["Dance", "Pop"],
    "title": "Look what you made me do",
    "artist": "Taylor Swift",
    "src": "https://musicfeed.ir/files/2020/01/Taylor-Swift-Look-What-You-Made-Me-Do-musicfeed.ir_.mp3",
    "cover": "assets/covers/look-what-you-made-me-do.png"
  },
  {
    "id": 10,
    "category": ["Chill", "Pop"],
    "title": "Style",
    "artist": "Taylor Swift",
    "src": "https://musicfeed.ir/files/dir/2020/11/Taylor%20Swift%20style.mp3",
    "cover": "assets/covers/style.png"
  },
  {
    "id": 11,
    "category": ["Pop"],
    "title": "You should see me in a crown",
    "artist": "Billie Eilish",
    "src": "https://musicfeed.ir/files/2020/02/Billie-Eilish-You-Should-See-Me-in-a-Crown-musicfeed.ir_.mp3",
    "cover": "assets/covers/you-should-see-me-in-a-crown.png"
  },
  {
    "id": 12,
    "category": ["Pop", "Slow", "Chill"],
    "title": "Everything I wanted",
    "artist": "Billie Eilish",
    "src": "https://musicfeed.ir/files/2019/11/Billie-Eilish-everything-i-wanted.mp3",
    "cover": "assets/covers/everything-i-wanted.png"
  },
  {
    "id": 13,
    "category": ["Pop", "Chill"],
    "title": "Hymm for the weekend",
    "artist": "Coldplay",
    "src": "https://musicfeed.ir/files/dir/2020/10/Coldplay%20Ft.%20Beyonc%C3%A9%20Hymn%20for%20the%20Weekend.mp3",
    "cover": "assets/covers/hymm-for-the-weekend.jpg"
  },
  {
    "id": 14,
    "category": ["Pop", "Dance"],
    "title": "Something just like this",
    "artist": "Coldplay",
    "src": "https://musicfeed.ir/files/2020/05/The-Chainsmokers-Coldplay-Something-Just-Like-This.mp3",
    "cover": "assets/covers/something-just-like-this.jpg"
  },
  {
    "id": 15,
    "category": ["Pop", "Dance"],
    "title": "No tears left to cry",
    "artist": "Ariana Grande",
    "src": "https://musicfeed.ir/files/2019/10/Ariana-Grande-No-Tears-Left-to-Cry.mp3",
    "cover": "assets/covers/no-tears-left-to-cry.jpg"
  },
  {
    "id": 16,
    "category": ["Acoustic", "Chill", "Slow"],
    "title": "Stuck with you",
    "artist": "Ariana Grande",
    "src": "https://musicfeed.ir/files/2020/05/Justin-Bieber-ft.-Ariana-Grande-Stuck-with-U.mp3",
    "cover": "assets/covers/stuck-with-you.jpg"
  },
  {
    "id": 17,
    "category": ["Rap"],
    "title": "Better now",
    "artist": "Post Malone",
    "src": "https://musicfeed.ir/files/2019/09/Post-Malone-Better-Now.mp3",
    "cover": "assets/covers/better-now.jpg"
  },
  {
    "id": 18,
    "category": ["Rap", "Dance"],
    "title": "Sunflower",
    "artist": "Post Malone",
    "src": "https://musicfeed.ir/files/2020/02/Post-Malone-Swae-Lee-Sunflower-musicfeed.ir_.mp3",
    "cover": "assets/covers/sunflower.jpg"
  },
  {
    "id": 19,
    "category": ["Rap", "Dance"],
    "title": "Let me love you",
    "artist": "Justin Bieber",
    "src": "https://musicfeed.ir/files/2020/02/DJ-Snake-Justin-Bieber-Let-me-love-you-musicfeed.ir_.mp3",
    "cover": "assets/covers/let-me-love-you.jpg"
  },
  {
    "id": 20,
    "category": ["Rap"],
    "title": "God's plan",
    "artist": "Drake",
    "src": "https://musicfeed.ir/files/2020/01/Drake-Gods-Plan-musicfeed.ir_.mp3",
    "cover": "assets/covers/gods-plan.jpg"
  }
]
